{
  "requestId": "ppt-assets-1784788668767-120ta0",
  "slideTitle": "Why is Nutrition Essential?",
  "slidePurpose": "core_concept",
  "semanticVisualQuery": "Why is Nutrition Essential? Importance of Nutrition Provides energy f...",
  "assetCountFromModel": 1,
  "keptAssetCount": 0,
  "assetDebugEntries": [
    {
      "assetIndex": 0,
      "requestedSearchQuery": "Why is Nutrition Essential? Importance of Nutrition Provides energy f...",
      "effectiveSearchQuery": "Why is Nutrition Essential? Importance of Nutrition Provides energy f...",
      "preferSvg": false,
      "needsResolution": true,
      "resolution": "wikimedia-miss",
      "sourceKind": "none"
    }
  ]
}