{
  "units": [
    {
      "unit_id": "U1",
      "classified_blocks": [
        {
          "source_heading": "Chapter I The Rise of Nationalism in Europe",
          "source_text_excerpt": "The Rise of Nationalism in Europe",
          "classification": "chapter",
          "confidence": 0.95,
          "parent_chapter": ""
        },
        {
          "source_heading": "Chapter II Nationalism in India",
          "source_text_excerpt": "Nationalism in India",
          "classification": "chapter",
          "confidence": 0.95,
          "parent_chapter": ""
        }
      ]
    },
    {
      "unit_id": "U2",
      "classified_blocks": [
        {
          "source_heading": "Chapter III The Making of a Global World",
          "source_text_excerpt": "The Making of a Global World",
          "classification": "chapter",
          "confidence": 0.95,
          "parent_chapter": ""
        },
        {
          "source_heading": "Chapter IV The Age of Industrialisation",
          "source_text_excerpt": "The Age of Industrialisation",
          "classification": "chapter",
          "confidence": 0.95,
          "parent_chapter": ""
        },
        {
          "source_heading": "Chapter V Print Culture and the Modern world",
          "source_text_excerpt": "Print Culture and the Modern world",
          "classification": "chapter",
          "confidence": 0.95,
          "parent_chapter": ""
        }
      ]
    }
  ]
}