{
  "subject": "Science",
  "gradeLevel": "Class IX",
  "selectedChapters": [
    "Tissues"
  ],
  "sessionNumber": 2,
  "totalSessions": 18,
  "durationMinutes": 45,
  "config": {
    "includeLearningOutcomes": true,
    "includeIntroduction": true,
    "includeTheory": true,
    "includeAssessments": true,
    "includeAssignments": false,
    "includeNotes": true
  },
  "selectedSections": [
    "studentLessonNotes"
  ],
  "sessionTitle": "Tissues - Session 2",
  "learningOutcomes": [],
  "previousSessionContext": "Cell and Cell Organelles - Session 1: Cells are the basic unit of life. Prokaryotes lack a nucleus; Eukaryotes have one. Cell membrane controls movement; Cell wall provides support in plants.",
  "teachingStrategy": {
    "studentLevel": "Grade-level mixed",
    "pace": "Balanced",
    "assessmentPreference": [
      "Worksheet-heavy"
    ],
    "targetDifficulty": "Balanced",
    "teachingStyle": [
      "Interactive facilitation",
      "Direct instruction",
      "Hands-on activity"
    ],
    "bloomsTaxonomyEmphasis": [
      "Remember + Understand"
    ],
    "teachingResources": [
      "Blackboard",
      "Charts / models",
      "Projector / PPT"
    ]
  },
  "sessionPlanningDefaults": {
    "sessionDurationMinutes": 45,
    "language": "English",
    "readingLevel": "Grade-aligned",
    "responseLength": "Detailed",
    "creativity": "Moderate",
    "includeRealWorldConnections": true,
    "includeDifferentiation": true,
    "includeFormativeAssessment": true,
    "includeHomework": true,
    "includeTeacherNotes": true
  },
  "assessmentCustomization": null,
  "sourceSessionPlan": null
}