{
  "dependency_graph": [
    {
      "topic": "Meaning and Significance of Accounting",
      "prerequisites": [],
      "dependent_topics": [
        "Accounting Terminology and Concepts"
      ]
    },
    {
      "topic": "Accounting Terminology and Concepts",
      "prerequisites": [
        "Meaning and Significance of Accounting"
      ],
      "dependent_topics": [
        "Accounting Transactions and Income Recognition"
      ]
    },
    {
      "topic": "Accounting Transactions and Income Recognition",
      "prerequisites": [
        "Accounting Terminology and Concepts"
      ],
      "dependent_topics": [
        "Accounting Assumptions and Standards"
      ]
    },
    {
      "topic": "Accounting Assumptions and Standards",
      "prerequisites": [
        "Accounting Transactions and Income Recognition"
      ],
      "dependent_topics": [
        "Recording Systems and Bases"
      ]
    },
    {
      "topic": "Recording Systems and Bases",
      "prerequisites": [
        "Accounting Assumptions and Standards"
      ],
      "dependent_topics": [
        "Goods and Services Tax (GST)"
      ]
    },
    {
      "topic": "Goods and Services Tax (GST)",
      "prerequisites": [
        "Recording Systems and Bases"
      ],
      "dependent_topics": []
    },
    {
      "topic": "Accounting Equation and Transaction Effects",
      "prerequisites": [],
      "dependent_topics": [
        "Vouchers and GST Calculation"
      ]
    },
    {
      "topic": "Vouchers and GST Calculation",
      "prerequisites": [
        "Accounting Equation and Transaction Effects"
      ],
      "dependent_topics": [
        "Cash Book and Subsidiary Books"
      ]
    },
    {
      "topic": "Cash Book and Subsidiary Books",
      "prerequisites": [
        "Vouchers and GST Calculation"
      ],
      "dependent_topics": [
        "Bank Reconciliation Statement"
      ]
    },
    {
      "topic": "Bank Reconciliation Statement",
      "prerequisites": [
        "Cash Book and Subsidiary Books"
      ],
      "dependent_topics": []
    },
    {
      "topic": "Depreciation Accounting Treatment",
      "prerequisites": [],
      "dependent_topics": [
        "Asset Disposal and Reserves"
      ]
    },
    {
      "topic": "Asset Disposal and Reserves",
      "prerequisites": [
        "Depreciation Accounting Treatment"
      ],
      "dependent_topics": []
    },
    {
      "topic": "Ledger Posting and Trial Balance",
      "prerequisites": [],
      "dependent_topics": [
        "Errors, Rectification and Suspense Account"
      ]
    },
    {
      "topic": "Errors, Rectification and Suspense Account",
      "prerequisites": [
        "Ledger Posting and Trial Balance"
      ],
      "dependent_topics": []
    },
    {
      "topic": "Meaning and Purpose of Financial Statements",
      "prerequisites": [],
      "dependent_topics": [
        "Trading, Profit and Loss Account Preparation"
      ]
    },
    {
      "topic": "Trading, Profit and Loss Account Preparation",
      "prerequisites": [
        "Meaning and Purpose of Financial Statements"
      ],
      "dependent_topics": []
    },
    {
      "topic": "Balance Sheet Preparation",
      "prerequisites": [],
      "dependent_topics": [
        "Adjustments in Financial Statements"
      ]
    },
    {
      "topic": "Adjustments in Financial Statements",
      "prerequisites": [
        "Balance Sheet Preparation"
      ],
      "dependent_topics": []
    },
    {
      "topic": "Incomplete Records Statement of Affairs",
      "prerequisites": [],
      "dependent_topics": []
    },
    {
      "topic": "Partnership Fundamentals and Deed",
      "prerequisites": [
        "Meaning and Significance of Accounting"
      ],
      "dependent_topics": [
        "Capital Accounts and Profit Distribution"
      ]
    },
    {
      "topic": "Capital Accounts and Profit Distribution",
      "prerequisites": [
        "Partnership Fundamentals and Deed"
      ],
      "dependent_topics": []
    },
    {
      "topic": "Goodwill Valuation",
      "prerequisites": [],
      "dependent_topics": []
    },
    {
      "topic": "Change in Profit Sharing Ratio",
      "prerequisites": [
        "Capital Accounts and Profit Distribution"
      ],
      "dependent_topics": [
        "Admission of a Partner"
      ]
    },
    {
      "topic": "Admission of a Partner",
      "prerequisites": [
        "Change in Profit Sharing Ratio"
      ],
      "dependent_topics": []
    },
    {
      "topic": "Retirement or Death of a Partner",
      "prerequisites": [],
      "dependent_topics": []
    },
    {
      "topic": "Dissolution of a Firm",
      "prerequisites": [
        "Admission of a Partner"
      ],
      "dependent_topics": []
    },
    {
      "topic": "Share Capital Types and Issue of Shares",
      "prerequisites": [],
      "dependent_topics": [
        "Forfeiture and Re-issue of Shares"
      ]
    },
    {
      "topic": "Forfeiture and Re-issue of Shares",
      "prerequisites": [
        "Share Capital Types and Issue of Shares"
      ],
      "dependent_topics": []
    },
    {
      "topic": "Debentures and Financial Statements",
      "prerequisites": [],
      "dependent_topics": []
    },
    {
      "topic": "Financial Statement Analysis Tools",
      "prerequisites": [
        "Meaning and Purpose of Financial Statements"
      ],
      "dependent_topics": []
    },
    {
      "topic": "Liquidity Ratios",
      "prerequisites": [],
      "dependent_topics": []
    },
    {
      "topic": "Solvency Ratios",
      "prerequisites": [
        "Financial Statement Analysis Tools"
      ],
      "dependent_topics": []
    },
    {
      "topic": "Activity Ratios",
      "prerequisites": [],
      "dependent_topics": []
    },
    {
      "topic": "Profitability Ratios",
      "prerequisites": [
        "Financial Statement Analysis Tools"
      ],
      "dependent_topics": []
    },
    {
      "topic": "Cash Flow Statement",
      "prerequisites": [],
      "dependent_topics": []
    },
    {
      "topic": "Introduction to CAS and Spreadsheets",
      "prerequisites": [
        "Meaning and Significance of Accounting"
      ],
      "dependent_topics": [
        "System Setup and Data Management"
      ]
    },
    {
      "topic": "System Setup and Data Management",
      "prerequisites": [
        "Introduction to CAS and Spreadsheets"
      ],
      "dependent_topics": []
    },
    {
      "topic": "System Security",
      "prerequisites": [],
      "dependent_topics": []
    }
  ],
  "lesson_planning_intelligence": [
    {
      "unit_name": "Theoretical Framework",
      "chapter_name": "Theoretical Framework",
      "difficulty_level": "Beginner",
      "concept_density": "High",
      "estimated_teaching_hours": "12-15 hours",
      "estimated_sessions": "6-8 sessions",
      "practical_requirement": "Low (Conceptual exercises)",
      "assessment_requirement": "Theory Questions on definitions and assumptions"
    },
    {
      "unit_name": "Accounting Process",
      "chapter_name": "Accounting Process",
      "difficulty_level": "Intermediate",
      "concept_density": "High",
      "estimated_teaching_hours": "20-25 hours",
      "estimated_sessions": "10-12 sessions",
      "practical_requirement": "Medium (Cash book, BRS preparation)",
      "assessment_requirement": "Problem-solving on transactions and adjustments"
    },
    {
      "unit_name": "Financial Statements of Sole Proprietorship",
      "chapter_name": "Financial Statements of Sole Proprietorship",
      "difficulty_level": "Intermediate to Advanced",
      "concept_density": "High",
      "estimated_teaching_hours": "18-20 hours",
      "estimated_sessions": "9-10 sessions",
      "practical_requirement": "Medium (Statement preparation)",
      "assessment_requirement": "Preparation of P&L and Balance Sheet with adjustments"
    },
    {
      "unit_name": "Accounting for Partnership Firms",
      "chapter_name": "Unit 1. Accounting for Partnership Firms",
      "difficulty_level": "Advanced",
      "concept_density": "Very High",
      "estimated_teaching_hours": "25-30 hours",
      "estimated_sessions": "12-14 sessions",
      "practical_requirement": "High (Complex calculations for goodwill, revaluation)",
      "assessment_requirement": "Case studies on admission, retirement, and dissolution"
    },
    {
      "unit_name": "Accounting for Companies",
      "chapter_name": "Unit 2. Accounting for Companies",
      "difficulty_level": "Advanced",
      "concept_density": "Very High",
      "estimated_teaching_hours": "15-18 hours",
      "estimated_sessions": "7-9 sessions",
      "practical_requirement": "High (Share capital and debenture accounting)",
      "assessment_requirement": "Journal entries for share issues, forfeiture, re-issue"
    },
    {
      "unit_name": "Analysis of Financial Statements",
      "chapter_name": "Unit 3. Analysis of Financial Statements",
      "difficulty_level": "Intermediate to Advanced",
      "concept_density": "High",
      "estimated_teaching_hours": "15-20 hours",
      "estimated_sessions": "8-10 sessions",
      "practical_requirement": "Medium (Ratio calculations)",
      "assessment_requirement": "Computation of ratios and cash flow statements"
    },
    {
      "unit_name": "Computerised Accounting",
      "chapter_name": "Unit 4. Computerised Accounting",
      "difficulty_level": "Intermediate",
      "concept_density": "Medium",
      "estimated_teaching_hours": "10-12 hours",
      "estimated_sessions": "5-6 sessions (Lab based)",
      "practical_requirement": "Very High (Software installation and data entry)",
      "assessment_requirement": "Practical file submission on CAS"
    }
  ],
  "validation_report": {
    "structural_source_of_truth_enforced": true,
    "invalid_unit_names": [],
    "invalid_chapter_names": []
  }
}