{
  "requestId": "generate-content-session-1784797563545-ykmkcf",
  "slideTitle": "Are You Really Moving?",
  "slidePurpose": "hook-slide",
  "semanticVisualQuery": "Are You Really Moving? Relative Motion Concept",
  "assetCountFromModel": 1,
  "keptAssetCount": 0,
  "assetDebugEntries": [
    {
      "assetIndex": 0,
      "modelSearchLabel": "train station platform view",
      "persistedSearchLabel": "",
      "persistedLabelIsBad": true,
      "modelLabelIsBad": false,
      "regeneratedSearchLabel": "science classroom experiment",
      "shouldRegenerateLabel": true,
      "effectiveSearchQuery": "science classroom experiment",
      "retrySearchQuery": "science classroom experiment",
      "preferSvg": false,
      "needsResolution": true,
      "resolution": "wikimedia-miss",
      "sourceKind": "none"
    }
  ]
}